fastsparse/__init__.py
fastsparse/_nbdev.py
fastsparse/core.py
fastsparse-0.0.5.dist-info/LICENSE
fastsparse-0.0.5.dist-info/METADATA
fastsparse-0.0.5.dist-info/WHEEL
fastsparse-0.0.5.dist-info/entry_points.txt
fastsparse-0.0.5.dist-info/top_level.txt
fastsparse-0.0.5.dist-info/RECORD
