Metadata-Version: 2.1
Name: fastsparse
Version: 0.0.5
Summary: Fastai+PyTorch implementation of sparse model training methods (SET, SNFS, and RigL).
Home-page: https://github.com/dcato98/fastsparse/tree/master/
Author: David Cato
Author-email: dcato98@gmail.com
License: Apache Software License 2.0
Keywords: sparse fastai fastai-implementation pytorch nbdev
Platform: UNKNOWN
Classifier: Development Status :: 3 - Alpha
Classifier: Intended Audience :: Developers
Classifier: License :: OSI Approved :: Apache Software License
Classifier: Natural Language :: English
Classifier: Programming Language :: Python :: 3.6
Classifier: Programming Language :: Python :: 3.7
Classifier: Programming Language :: Python :: 3.8
Requires-Python: >=3.6
Requires-Dist: fastai
